vnm/__init__.py
vnm/__main__.py
vnm/constraint.py
vnm/consts.py
vnm/package.py
vnm/state.py
vnm/utils.py
vnm/venv.py
vnm/repos/__init__.py
vnm/repos/git.py
vnm/repos/repo.py
vnm/repos/wheel.py
vnm-0.5.1.dist-info/METADATA
vnm-0.5.1.dist-info/WHEEL
vnm-0.5.1.dist-info/entry_points.txt
vnm-0.5.1.dist-info/top_level.txt
vnm-0.5.1.dist-info/RECORD
