Metadata-Version: 2.1
Name: vnm
Version: 0.5.1
Summary: UNKNOWN
Home-page: UNKNOWN
Author: Rob "N3X15" Nelson
Author-email: nexisentertainment@gmail.com
License: MIT
Platform: UNKNOWN
Requires-Dist: pip (==21.0.1)
Requires-Dist: setuptools (==54.2.0)
Requires-Dist: wheel (==0.36.2)
Requires-Dist: ruamel.yaml (==0.17.2)
